MANIFEST.in
README.rst
setup.cfg
setup.py
portmanager/__init__.py
portmanager/admin.py
portmanager/filtersets.py
portmanager/forms.py
portmanager/models.py
portmanager/navigation.py
portmanager/tables.py
portmanager/template_code.py
portmanager/urls.py
portmanager/utils.py
portmanager/views.py
portmanager.egg-info/PKG-INFO
portmanager.egg-info/SOURCES.txt
portmanager.egg-info/dependency_links.txt
portmanager.egg-info/not-zip-safe
portmanager.egg-info/requires.txt
portmanager.egg-info/top_level.txt
portmanager/api/__init__.py
portmanager/api/serializers.py
portmanager/api/urls.py
portmanager/api/views.py
portmanager/migrations/0001_initial.py
portmanager/migrations/__init__.py
portmanager/static/portmanager/img/connected.png
portmanager/static/portmanager/img/disabled.png
portmanager/static/portmanager/img/notconnected.png
portmanager/switches/__init__.py
portmanager/switches/cisco_switch.py
portmanager/switches/general_switch.py
portmanager/switches/interface.py
portmanager/switches/utils.py
portmanager/switches/vlan.py
portmanager/templates/portmanager/device.html
portmanager/templates/portmanager/device_object.html
portmanager/templates/portmanager/devicegroup.html
portmanager/templates/portmanager/mac.html
portmanager/templates/portmanager/changelog/changelog.html
portmanager/templates/portmanager/generic/object.html
portmanager/templates/portmanager/htmx/table.html
portmanager/templates/portmanager/inc/paginator_htmx.html
portmanager/templates/portmanager/inc/table_htmx.html
portmanager/templatetags/portmanager_filters.py