Metadata-Version: 2.1
Name: portmanager
Version: 1.4.5
Summary: Netbox Portmanager
Home-page: https://github.com/dansheps/netbox-secretstore/
Author: Michal Drobny
Author-email: ddrobny@ics.muni.cz
License: Apache 2.0
Download-URL: https://www.pypi.org/project/netbox-secretstore/
Platform: UNKNOWN
Classifier: Programming Language :: Python :: 3
Classifier: License :: OSI Approved :: MIT License
Classifier: Operating System :: OS Independent
Requires-Python: >=3.8
